[
    {
        "title": "Iran threatens to block more trade routes as US launches fresh strikes",
        "link": "https://www.bbc.co.uk/news/articles/c9323zgq6wvo?at_medium=RSS&at_campaign=rss",
        "image": "https://ichef.bbci.co.uk/ace/branded_news/1200/cpsprodpb/c484/live/46eda4a0-8059-11f1-bee8-53ce494e1abc.jpg",
        "published": "Wed, 15 Jul 2026 12:26:38 GMT"
    },
    {
        "title": "Trump retreat over Hormuz tolls suggests he is struggling to end Iran war",
        "link": "https://www.bbc.co.uk/news/articles/crele3r8j19o?at_medium=RSS&at_campaign=rss",
        "image": "https://ichef.bbci.co.uk/ace/branded_news/1200/cpsprodpb/87df/live/cb49bc70-7fc8-11f1-82bc-eb96a9eb8087.jpg",
        "published": "Tue, 14 Jul 2026 23:17:27 GMT"
    },
    {
        "title": "Strait of Hormuz 'faultline' exposes weakness of the US-Iran deal",
        "link": "https://www.bbc.co.uk/news/articles/cwy0ydn033yo?at_medium=RSS&at_campaign=rss",
        "image": "https://ichef.bbci.co.uk/ace/branded_news/1200/cpsprodpb/2d0c/live/39f9d170-7fa9-11f1-a5f4-433bb9aa2e5a.jpg",
        "published": "Tue, 14 Jul 2026 19:13:49 GMT"
    },
    {
        "title": "Russian attacks kill eight as Ukraine hits Black Sea oil tankers",
        "link": "https://www.bbc.co.uk/news/articles/c8929jv8kdzo?at_medium=RSS&at_campaign=rss",
        "image": "https://ichef.bbci.co.uk/ace/branded_news/1200/cpsprodpb/d14b/live/76285910-802f-11f1-a2a1-e90920ef9667.jpg",
        "published": "Wed, 15 Jul 2026 13:32:05 GMT"
    },
    {
        "title": "Special police team to investigate killing of an anti-migrant leader in South Africa",
        "link": "https://www.bbc.co.uk/news/articles/cm2d2qlgj71o?at_medium=RSS&at_campaign=rss",
        "image": "https://ichef.bbci.co.uk/ace/branded_news/1200/cpsprodpb/233b/live/4e691b90-8056-11f1-bee8-53ce494e1abc.jpg",
        "published": "Wed, 15 Jul 2026 14:37:45 GMT"
    },
    {
        "title": "Italy's Meloni suffers surprise setback in close vote on electoral reform",
        "link": "https://www.bbc.co.uk/news/articles/c1kykx3vnyyo?at_medium=RSS&at_campaign=rss",
        "image": "https://ichef.bbci.co.uk/ace/branded_news/1200/cpsprodpb/8aee/live/f5abe350-8039-11f1-86b6-ffbb9ce74513.jpg",
        "published": "Wed, 15 Jul 2026 11:44:28 GMT"
    },
    {
        "title": "Rastafarians in Kenya fail in bid to get cannabis legalised for religious purposes",
        "link": "https://www.bbc.co.uk/news/articles/c0lyl5ryyr4o?at_medium=RSS&at_campaign=rss",
        "image": "https://ichef.bbci.co.uk/ace/branded_news/1200/cpsprodpb/40bf/live/f5625400-8035-11f1-b976-0b9c15b0ccfc.jpg",
        "published": "Wed, 15 Jul 2026 10:50:09 GMT"
    },
    {
        "title": "Venezuela government to launch formal talks with opposition members",
        "link": "https://www.bbc.co.uk/news/articles/c1eye5320g5o?at_medium=RSS&at_campaign=rss",
        "image": "https://ichef.bbci.co.uk/ace/branded_news/1200/cpsprodpb/5dbd/live/b45bfff0-803b-11f1-ad4e-5b151eaf0c69.jpg",
        "published": "Wed, 15 Jul 2026 12:21:21 GMT"
    },
    {
        "title": "China economic growth falls sharply, missing target",
        "link": "https://www.bbc.co.uk/news/articles/cd959x4edy8o?at_medium=RSS&at_campaign=rss",
        "image": "https://ichef.bbci.co.uk/ace/branded_news/1200/cpsprodpb/c8de/live/7e6a3480-7f40-11f1-ba68-9b76167cb04b.jpg",
        "published": "Wed, 15 Jul 2026 10:21:48 GMT"
    },
    {
        "title": "Heatwave prompts Italy's delivery riders to strike for extra rights",
        "link": "https://www.bbc.co.uk/news/articles/c1dydw0r246o?at_medium=RSS&at_campaign=rss",
        "image": "https://ichef.bbci.co.uk/ace/branded_news/1200/cpsprodpb/d193/live/da486780-803b-11f1-ad4e-5b151eaf0c69.jpg",
        "published": "Wed, 15 Jul 2026 11:38:37 GMT"
    },
    {
        "title": "Sierra Leone drops treason charge against ex-president over attempted coup",
        "link": "https://www.bbc.co.uk/news/articles/cx2w2k3vklgo?at_medium=RSS&at_campaign=rss",
        "image": "https://ichef.bbci.co.uk/ace/branded_news/1200/cpsprodpb/8cd1/live/0dc02dc0-8030-11f1-bee8-53ce494e1abc.jpg",
        "published": "Wed, 15 Jul 2026 11:43:15 GMT"
    },
    {
        "title": "Air India crash report likely to be ready in October, say investigators",
        "link": "https://www.bbc.co.uk/news/articles/cjrgrgx2d9qo?at_medium=RSS&at_campaign=rss",
        "image": "https://ichef.bbci.co.uk/ace/branded_news/1200/cpsprodpb/0d29/live/a6d13090-8012-11f1-855c-e18bf6105698.jpg",
        "published": "Wed, 15 Jul 2026 09:45:21 GMT"
    },
    {
        "title": "Seven Britons among those killed in Spain wildfires",
        "link": "https://www.bbc.co.uk/news/articles/cp8l87784ngo?at_medium=RSS&at_campaign=rss",
        "image": "https://ichef.bbci.co.uk/ace/branded_news/1200/cpsprodpb/dfc7/live/8d789890-8017-11f1-bee8-53ce494e1abc.jpg",
        "published": "Wed, 15 Jul 2026 12:21:32 GMT"
    },
    {
        "title": "Boss of fake government agency arrested in Nigeria after weeks on the run",
        "link": "https://www.bbc.co.uk/news/articles/c17y7ykzgrgo?at_medium=RSS&at_campaign=rss",
        "image": "https://ichef.bbci.co.uk/ace/branded_news/1200/cpsprodpb/c4f3/live/b190b220-8013-11f1-855c-e18bf6105698.jpg",
        "published": "Wed, 15 Jul 2026 09:42:09 GMT"
    },
    {
        "title": "China detains US scientist who studied North Korea nuclear tests",
        "link": "https://www.bbc.co.uk/news/articles/cqx1xdn3g4eo?at_medium=RSS&at_campaign=rss",
        "image": "https://ichef.bbci.co.uk/ace/branded_news/1200/cpsprodpb/8707/live/0aa9b510-8027-11f1-b976-0b9c15b0ccfc.jpg",
        "published": "Wed, 15 Jul 2026 02:14:37 GMT"
    }
]