[
    {
        "title": "A decade on, Trump returns to a stronger and more assertive China",
        "link": "https://www.bbc.com/news/articles/cm2py6l78dxo?at_medium=RSS&at_campaign=rss",
        "image": "https://ichef.bbci.co.uk/news/1024/branded_news/a764/live/ecd6a5e0-4e01-11f1-aa37-6b8846c2f74e.jpg",
        "published": "Tue, 12 May 2026 22:07:51 GMT"
    },
    {
        "title": "Australia has some of the world's costliest homes. Will scrapping tax breaks help?",
        "link": "https://www.bbc.com/news/articles/cd7p88j84j3o?at_medium=RSS&at_campaign=rss",
        "image": "https://ichef.bbci.co.uk/news/1024/branded_news/6ded/live/01840610-4e91-11f1-ac78-2112837ce2aa.jpg",
        "published": "Tue, 12 May 2026 20:28:03 GMT"
    },
    {
        "title": "Air India crisis deepens ahead of final Ahmedabad crash report",
        "link": "https://www.bbc.com/news/articles/c775vvz0kydo?at_medium=RSS&at_campaign=rss",
        "image": "https://ichef.bbci.co.uk/news/1024/branded_news/59ad/live/94b20f80-4db6-11f1-8e66-f56d9b46fa9c.jpg",
        "published": "Tue, 12 May 2026 22:15:50 GMT"
    },
    {
        "title": "Jason Collins, NBA's first openly gay player, dies aged 47",
        "link": "https://www.bbc.com/news/articles/clyp8rdldk1o?at_medium=RSS&at_campaign=rss",
        "image": "https://ichef.bbci.co.uk/news/1024/branded_news/4f53/live/0b673990-4e5f-11f1-b3b3-0b50bfaa6ecf.jpg",
        "published": "Wed, 13 May 2026 00:40:54 GMT"
    },
    {
        "title": "Lebanon says two paramedics among 13 killed in Israeli strikes",
        "link": "https://www.bbc.com/news/articles/cx21j3xl72zo?at_medium=RSS&at_campaign=rss",
        "image": "https://ichef.bbci.co.uk/news/1024/branded_news/e3ef/live/68ba80e0-4e1c-11f1-b55d-0f258dce1735.jpg",
        "published": "Tue, 12 May 2026 20:00:05 GMT"
    },
    {
        "title": "Trump's 'Golden Dome' will cost $1.2tn and might not stop all-out missile attack",
        "link": "https://www.bbc.com/news/articles/cqxp27j1xyjo?at_medium=RSS&at_campaign=rss",
        "image": "https://ichef.bbci.co.uk/news/1024/branded_news/f040/live/d4bf8df0-4e5b-11f1-9305-3566b5d14ae1.jpg",
        "published": "Wed, 13 May 2026 01:59:53 GMT"
    },
    {
        "title": "Zelensky's ex-chief of staff in court as Ukraine corruption probe escalates",
        "link": "https://www.bbc.com/news/articles/c4g48kj40lwo?at_medium=RSS&at_campaign=rss",
        "image": "https://ichef.bbci.co.uk/news/1024/branded_news/815a/live/6abed600-4e14-11f1-bd2e-5b25b00aa23c.jpg",
        "published": "Tue, 12 May 2026 16:19:24 GMT"
    },
    {
        "title": "Thief jailed after stealing unreleased Beyonc\u00e9 music from car",
        "link": "https://www.bbc.com/news/articles/cx213vnvxvwo?at_medium=RSS&at_campaign=rss",
        "image": "https://ichef.bbci.co.uk/news/1024/branded_news/df5d/live/26be9cb0-4e37-11f1-8aa2-99cac85d32c6.jpg",
        "published": "Wed, 13 May 2026 00:01:04 GMT"
    },
    {
        "title": "No sign of larger hantavirus outbreak, says UN health agency",
        "link": "https://www.bbc.com/news/articles/cqjpqynj1nlo?at_medium=RSS&at_campaign=rss",
        "image": "https://ichef.bbci.co.uk/news/1024/branded_news/62d4/live/48741b80-4dee-11f1-8191-8bac3ae59130.jpg",
        "published": "Tue, 12 May 2026 17:55:12 GMT"
    },
    {
        "title": "Hamas 'weaponised' sexual violence in 7 October attacks, Israeli investigation says",
        "link": "https://www.bbc.com/news/articles/cvgz9k7pzggo?at_medium=RSS&at_campaign=rss",
        "image": "https://ichef.bbci.co.uk/news/1024/branded_news/efcd/live/2bb72400-4e0d-11f1-ac78-2112837ce2aa.jpg",
        "published": "Tue, 12 May 2026 16:58:51 GMT"
    },
    {
        "title": "Dali ship operator charged over deadly  Baltimore bridge collapse",
        "link": "https://www.bbc.com/news/articles/cnvpm67ner6o?at_medium=RSS&at_campaign=rss",
        "image": "https://ichef.bbci.co.uk/news/1024/branded_news/d233/live/00bb5c20-4e13-11f1-bd2e-5b25b00aa23c.jpg",
        "published": "Tue, 12 May 2026 18:03:54 GMT"
    },
    {
        "title": "eBay rejects $55.5bn offer from GameStop",
        "link": "https://www.bbc.com/news/articles/ckgp5ll3jd4o?at_medium=RSS&at_campaign=rss",
        "image": "https://ichef.bbci.co.uk/news/1024/branded_news/fe29/live/02e51490-4e00-11f1-aa37-6b8846c2f74e.jpg",
        "published": "Tue, 12 May 2026 14:07:18 GMT"
    },
    {
        "title": "Uganda's president sworn in for record seventh term",
        "link": "https://www.bbc.com/news/articles/cqxp23272j3o?at_medium=RSS&at_campaign=rss",
        "image": "https://ichef.bbci.co.uk/news/1024/branded_news/b319/live/3e3c40b0-4e12-11f1-ac78-2112837ce2aa.jpg",
        "published": "Tue, 12 May 2026 14:58:18 GMT"
    },
    {
        "title": "South Africa's top court bars repeat asylum applications",
        "link": "https://www.bbc.com/news/articles/cy42yx1kn90o?at_medium=RSS&at_campaign=rss",
        "image": "https://ichef.bbci.co.uk/news/1024/branded_news/e0fc/live/23acc040-4e20-11f1-ac78-2112837ce2aa.jpg",
        "published": "Tue, 12 May 2026 16:38:53 GMT"
    },
    {
        "title": "EU needs to delay social media access for children - von der Leyen",
        "link": "https://www.bbc.com/news/articles/c9q3x19ddl7o?at_medium=RSS&at_campaign=rss",
        "image": "https://ichef.bbci.co.uk/news/1024/branded_news/8d26/live/7afc2660-4de9-11f1-9cc8-93479330ab4b.jpg",
        "published": "Tue, 12 May 2026 11:00:34 GMT"
    }
]