[
    {
        "title": "US and Iran 'very close' to deal but 'not there yet', Vance says",
        "link": "https://www.bbc.com/news/articles/c87qng40wz9o?at_medium=RSS&at_campaign=rss",
        "image": "https://ichef.bbci.co.uk/news/1024/branded_news/d0cd/live/13cf4080-5aeb-11f1-b8b0-e75ba6be4215.jpg",
        "published": "Thu, 28 May 2026 23:32:19 GMT"
    },
    {
        "title": "Are US and Iran close to peace or sliding back to war?",
        "link": "https://www.bbc.com/news/articles/cze29764067o?at_medium=RSS&at_campaign=rss",
        "image": "https://ichef.bbci.co.uk/news/1024/branded_news/4b47/live/14febc40-5a9d-11f1-8b8c-6d33e1d5abb6.jpg",
        "published": "Thu, 28 May 2026 16:56:19 GMT"
    },
    {
        "title": "Gaza City hospitals say several killed in strike, as Israel targets Hamas leaders",
        "link": "https://www.bbc.com/news/articles/cn9p40en4ngo?at_medium=RSS&at_campaign=rss",
        "image": "https://ichef.bbci.co.uk/news/1024/branded_news/ac09/live/d65f99a0-5aa1-11f1-9626-f75d5d5577d2.jpg",
        "published": "Thu, 28 May 2026 16:20:50 GMT"
    },
    {
        "title": "Learning from Ukraine war, Hezbollah is now using fibre-optic drones to hit Israel",
        "link": "https://www.bbc.com/news/articles/c0r2ydlvk41o?at_medium=RSS&at_campaign=rss",
        "image": "https://ichef.bbci.co.uk/news/1024/branded_news/0c63/live/e5a53b30-5a84-11f1-b721-e3714617440a.jpg",
        "published": "Thu, 28 May 2026 16:39:30 GMT"
    },
    {
        "title": "Man jailed for 15 years over plot to attack Taylor Swift concert in Vienna",
        "link": "https://www.bbc.com/news/articles/cgrp7y05l9do?at_medium=RSS&at_campaign=rss",
        "image": "https://ichef.bbci.co.uk/news/1024/branded_news/fc5c/live/b948c050-5ad6-11f1-8b8c-6d33e1d5abb6.jpg",
        "published": "Thu, 28 May 2026 21:07:46 GMT"
    },
    {
        "title": "Villas, cars and cash: Italy seizes dead Mafia mobster's millions",
        "link": "https://www.bbc.com/news/articles/ceqpd4gqgveo?at_medium=RSS&at_campaign=rss",
        "image": "https://ichef.bbci.co.uk/news/1024/branded_news/cdae/live/4e668fc0-5a94-11f1-b5ae-83d5964726ad.jpg",
        "published": "Thu, 28 May 2026 14:47:05 GMT"
    },
    {
        "title": "Portugal breaks hottest May day record as Europe swelters in heatwave",
        "link": "https://www.bbc.com/news/articles/c3v2yv5207xo?at_medium=RSS&at_campaign=rss",
        "image": "https://ichef.bbci.co.uk/news/1024/branded_news/e6bd/live/11b1bcb0-5ab4-11f1-89a3-d1f559421220.jpg",
        "published": "Thu, 28 May 2026 23:36:01 GMT"
    },
    {
        "title": "Israel hits Lebanese capital in 'targeted strike'",
        "link": "https://www.bbc.com/news/articles/cgqpjwdv7xeo?at_medium=RSS&at_campaign=rss",
        "image": "https://ichef.bbci.co.uk/news/1024/branded_news/2412/live/e8e37ed0-5a9b-11f1-9626-f75d5d5577d2.jpg",
        "published": "Thu, 28 May 2026 17:39:16 GMT"
    },
    {
        "title": "Man arrested after three injured in stabbing at Swiss train station",
        "link": "https://www.bbc.com/news/articles/cddpllqv49qo?at_medium=RSS&at_campaign=rss",
        "image": "https://ichef.bbci.co.uk/news/1024/branded_news/5670/live/81cbabd0-5a9d-11f1-89a3-d1f559421220.jpg",
        "published": "Thu, 28 May 2026 16:26:14 GMT"
    },
    {
        "title": "Questions over safety as 16 pupils die in another Kenya school fire",
        "link": "https://www.bbc.com/news/articles/cx21kkxq81po?at_medium=RSS&at_campaign=rss",
        "image": "https://ichef.bbci.co.uk/news/1024/branded_news/444e/live/fe58c650-5a8f-11f1-8b8c-6d33e1d5abb6.jpg",
        "published": "Thu, 28 May 2026 16:28:29 GMT"
    },
    {
        "title": "Jill Biden says she thought husband was having a stroke during 2024 debate",
        "link": "https://www.bbc.com/news/articles/c99l270vy3no?at_medium=RSS&at_campaign=rss",
        "image": "https://ichef.bbci.co.uk/news/1024/branded_news/4f04/live/8d909940-5a0b-11f1-8958-3b1169652509.jpg",
        "published": "Thu, 28 May 2026 04:53:51 GMT"
    },
    {
        "title": "Australia charges woman who returned from Syria with joining Islamic State",
        "link": "https://www.bbc.com/news/articles/c87q2w0w0jvo?at_medium=RSS&at_campaign=rss",
        "image": "https://ichef.bbci.co.uk/news/1024/branded_news/76cc/live/bb8db440-5a47-11f1-8d7c-61e7f5f32f93.jpg",
        "published": "Thu, 28 May 2026 04:01:17 GMT"
    },
    {
        "title": "EU fines Temu \u20ac200m for allowing sale of illegal products",
        "link": "https://www.bbc.com/news/articles/c1k2ydn1rz8o?at_medium=RSS&at_campaign=rss",
        "image": "https://ichef.bbci.co.uk/news/1024/branded_news/6b44/live/c457e920-5a82-11f1-8b8c-6d33e1d5abb6.jpg",
        "published": "Thu, 28 May 2026 14:54:50 GMT"
    },
    {
        "title": "Australia sues US giant 3M over 'forever chemicals' in firefighting foam",
        "link": "https://www.bbc.com/news/articles/c3w2yl3p97qo?at_medium=RSS&at_campaign=rss",
        "image": "https://ichef.bbci.co.uk/news/1024/branded_news/36b1/live/ae442610-5a3e-11f1-b732-0194951cb5d3.jpg",
        "published": "Thu, 28 May 2026 02:47:19 GMT"
    },
    {
        "title": "Google worker charged with using internal data to make $1.2m on bets",
        "link": "https://www.bbc.com/news/articles/c052yv259jvo?at_medium=RSS&at_campaign=rss",
        "image": "https://ichef.bbci.co.uk/news/1024/branded_news/393c/live/7188c480-5a78-11f1-8b8c-6d33e1d5abb6.jpg",
        "published": "Thu, 28 May 2026 02:14:19 GMT"
    }
]